README.md
setup.py
once_utils.egg-info/PKG-INFO
once_utils.egg-info/SOURCES.txt
once_utils.egg-info/dependency_links.txt
once_utils.egg-info/top_level.txt
onceutils/__init__.py
onceutils/_cmd.py
onceutils/_convert.py
onceutils/_iter.py
onceutils/_pymodule.py
onceutils/_random.py
onceutils/const.py
onceutils/ex_dict.py
onceutils/http/__init__.py
onceutils/http/_http_raw.py
onceutils/xjson/__init__.py
onceutils/xjson/_common.py
onceutils/xjson/encoder.py
tests/test_cmd.py
tests/test_dict.py
tests/test_http_raw.py
tests/test_iter.py
tests/test_random.py
tests/test_xjson.py